indicator_management/__init__.py
indicator_management/_types.py
indicator_management/errors.py
indicator_management/graph.py
indicator_management/orchestration.py
indicator_management/plot.py
indicator_management/settings.py
indicator_management/utils.py
indicator_management/indicators/__init__.py
indicator_management/indicators/aging.py
indicator_management/indicators/base.py
indicator_management/indicators/comparisons.py
indicator_management/indicators/financial.py
indicator_management/indicators/mathematical.py
indicator_management/indicators/statistical.py
indicator_management/indicators/utils.py
indicator_management-0.6.1.dist-info/LICENSE
indicator_management-0.6.1.dist-info/METADATA
indicator_management-0.6.1.dist-info/WHEEL
indicator_management-0.6.1.dist-info/top_level.txt
indicator_management-0.6.1.dist-info/RECORD
