Metadata-Version: 2.1
Name: indicator-management
Version: 0.6.1
Summary: A library to help management of fully customized indicators
Home-page: https://github.com/McDic/IndicatorManagement
Author: McDic
Author-email: spongbob9876@naver.com
License: UNKNOWN
Project-URL: Bug Tracker, https://github.com/McDic/IndicatorManagement/issues
Platform: UNKNOWN
Classifier: Development Status :: 2 - Pre-Alpha
Classifier: Programming Language :: Python :: 3.10
Classifier: License :: OSI Approved :: GNU General Public License v3 or later (GPLv3+)
Classifier: Operating System :: OS Independent
Classifier: Intended Audience :: Financial and Insurance Industry
Classifier: Natural Language :: English
Classifier: Natural Language :: Korean
Classifier: Topic :: Office/Business :: Financial
Classifier: Topic :: Software Development :: Libraries
Classifier: Framework :: Matplotlib
Requires-Python: >=3.10
License-File: LICENSE
Requires-Dist: matplotlib (>=3.5.1)
Requires-Dist: sortedcontainers (>=2.4.0)
